component_tags_tailwindcss/__init__.py
component_tags_tailwindcss/admin.py
component_tags_tailwindcss/apps.py
component_tags_tailwindcss/components.py
component_tags_tailwindcss/models.py
component_tags_tailwindcss/tags.py
component_tags_tailwindcss/tests.py
component_tags_tailwindcss/widgets.py
component_tags_tailwindcss/migrations/__init__.py
component_tags_tailwindcss/static/component_tags_tailwindcss/css/base.css
component_tags_tailwindcss/static/component_tags_tailwindcss/css/base.min.css
component_tags_tailwindcss/static/component_tags_tailwindcss/css/components.css
component_tags_tailwindcss/static/component_tags_tailwindcss/css/components.min.css
component_tags_tailwindcss/static/component_tags_tailwindcss/css/tailwind-dark.css
component_tags_tailwindcss/static/component_tags_tailwindcss/css/tailwind-dark.min.css
component_tags_tailwindcss/static/component_tags_tailwindcss/css/tailwind-experimental.css
component_tags_tailwindcss/static/component_tags_tailwindcss/css/tailwind-experimental.min.css
component_tags_tailwindcss/static/component_tags_tailwindcss/css/tailwind.css
component_tags_tailwindcss/static/component_tags_tailwindcss/css/tailwind.min.css
component_tags_tailwindcss/static/component_tags_tailwindcss/css/utilities.css
component_tags_tailwindcss/static/component_tags_tailwindcss/css/utilities.min.css
component_tags_tailwindcss/static/component_tags_tailwindcss/js/alpine-ie11.js
component_tags_tailwindcss/static/component_tags_tailwindcss/js/alpine.js
component_tags_tailwindcss/templates/component_tags_tailwindcss/base.html
component_tags_tailwindcss/templates/component_tags_tailwindcss/tags/alert.html
component_tags_tailwindcss/templates/component_tags_tailwindcss/tags/badge.html
component_tags_tailwindcss/templates/component_tags_tailwindcss/tags/breadcrumb.html
component_tags_tailwindcss/templates/component_tags_tailwindcss/tags/breadcrumb_item.html
component_tags_tailwindcss/templates/component_tags_tailwindcss/tags/button.html
django_component_tags_tailwindcss-0.0.3.dist-info/AUTHORS.rst
django_component_tags_tailwindcss-0.0.3.dist-info/LICENSE.txt
django_component_tags_tailwindcss-0.0.3.dist-info/METADATA
django_component_tags_tailwindcss-0.0.3.dist-info/WHEEL
django_component_tags_tailwindcss-0.0.3.dist-info/top_level.txt
django_component_tags_tailwindcss-0.0.3.dist-info/RECORD
